LICENSE
MANIFEST.in
README.md
setup.py
unakite/__init__.py
unakite/app.py
unakite/handlers.py
unakite.egg-info/PKG-INFO
unakite.egg-info/SOURCES.txt
unakite.egg-info/dependency_links.txt
unakite.egg-info/requires.txt
unakite.egg-info/top_level.txt